[{
	"src":"http://pic.giftport.com.cn/giftimages/product/160x160/04878_01.jpg",
	"name":"黄则和凤梨酥 210g ", 
	"names":"[3盒39元]",
	"price":"¥14.00",
	"prices":"¥17.00",
	"Id":"0000"
	
},{
	"src":"http://pic.giftport.com.cn/giftimages/product/160x160/00015_01.jpg",
	"name":"佰翔空厨椰子饼220g", 
	"names":"[任意3盒39]",
	"price":"¥15.80",
	"prices":"¥18.00",
	"Id":"0001"
	
},{
	"src":"http://pic.giftport.com.cn/giftimages/product/160x160/04289_01.jpg",
	"name":" 赵小姐的绿豆馅饼198g", 
	"names":"<span>赵小姐的店，纪念儿时的鼓浪屿</span>",
	"price":"¥20.00",
	"prices":"¥20.00",
	"Id":"0002"
	
},{
	"src":"http://pic.giftport.com.cn/giftimages/product/160x160/04810_01.jpg",
	"name":"林菽莊伊豆酥210g", 
	"names":"包装升级，新旧包装随机发货",
	"price":"¥48.00",
	"prices":"¥48.00",
	"Id":"0003"
	
},{
	"src":"http://pic.giftport.com.cn/giftimages/product/160x160/00003_01.jpg",
	"name":"日光岩馅饼6盒装1200g", 
	"names":"口味随机，请以实物为准。",
	"price":"¥48.00",
	"prices":"¥45.00",
	"Id":"0004"
	
},{
	"src":"http://pic.giftport.com.cn/giftimages/product/160x160/03425_01.jpg",
	"name":"黄则和经典礼盒800g", 
	"names":"5种美食集合",
	"price":"¥49.00",
	"prices":"¥55.00",
	"Id":"0005"
	
}]
